squashpickle.py
squashpickle-0.1.2.dist-info/licenses/LICENSE.md
squashpickle-0.1.2.dist-info/METADATA
squashpickle-0.1.2.dist-info/WHEEL
squashpickle-0.1.2.dist-info/top_level.txt
squashpickle-0.1.2.dist-info/RECORD
