Metadata-Version: 2.4
Name: squashpickle
Version: 0.1.2
Summary: GZIP compressed pickle serialization.
Author-email: "CreatingNull (Steve Richardson)" <steve.public@nulltek.xyz>
License-Expression: MIT
Project-URL: homepage, https://github.com/CreatingNull/squash-pickle
Keywords: pickle,compression,gzip,gz,squash
Classifier: Programming Language :: Python :: 3
Requires-Python: >=3.9
License-File: LICENSE.md
Dynamic: license-file
